<?xml version="1.0" encoding="UTF-8"?>
<interface>
  <object class="GtkMenu" id="menu">
    <child>
        <object class="GtkMenuItem" id="mute_output">
            <property name="label">Un/Mute Vol</property>
        </object>
    </child>
    <child>
        <object class="GtkMenuItem" id="mute_input">
            <property name="label">Un/Mute Mic</property>
        </object>
    </child>
    <child>
      <object class="GtkSeparatorMenuItem" id="delimiter2"/>
    </child>
    <child>
        <object class="GtkMenuItem" id="control_panel">
            <property name="label">Volume Control</property>
        </object>
    </child>
  </object>
</interface>